{
    "physics":[
        {
            "_id": "easy_1",
            "difficulty": "easy",
            "question": "physics easy question (1)",
            "answer": "1",
            "options": [
                "1",
                "2",
                "3",
                "4"
            ],
            "topic": "optics"
        },
        {
            "_id": "hard_2",
            "difficulty": "hard",
            "question": "physics hard question (2)",
            "answer": "2",
            "options": [
                "1",
                "2",
                "3",
                "4"
            ],
            "topic": "optics"
        },
        {
            "_id": "medium_3",
            "difficulty": "medium",
            "question": "physics medium question (3)",
            "answer": "3",
            "options": [
                "1",
                "2",
                "3",
                "4"
            ],
            "topic": "optics"
        },
        {
            "_id": "easy_4",
            "difficulty": "easy",
            "question": "physics easy question (4)",
            "answer": "4",
            "options": [
                "1",
                "2",
                "3",
                "4"
            ],
            "topic": "optics"
        },
        {
            "_id": "medium_5",
            "difficulty": "medium",
            "question": "physics medium question (5)",
            "answer": "1",
            "options": [
                "1",
                "2",
                "3",
                "4"
            ],
            "topic": "optics"
        },
        {
            "_id": "easy_6",
            "difficulty": "easy",
            "question": "physics easy question (6)",
            "answer": "2",
            "options": [
                "1",
                "2",
                "3",
                "4"
            ],
            "topic": "mechanics"
        },
        {
            "_id": "easy_7",
            "difficulty": "easy",
            "question": "physics easy question (7)",
            "answer": "3",
            "options": [
                "1",
                "2",
                "3",
                "4"
            ],
            "topic": "mechanics"
        },
        {
            "_id": "hard_8",
            "difficulty": "hard",
            "question": "physics hard question (8)",
            "answer": "4",
            "options": [
                "1",
                "2",
                "3",
                "4"
            ],
            "topic": "mechanics"
        },
        {
            "_id": "medium_9",
            "difficulty": "medium",
            "question": "physics medium question (9)",
            "answer": "1",
            "options": [
                "1",
                "2",
                "3",
                "4"
            ],
            "topic": "mechanics"
        },
        {
            "_id": "easy_10",
            "difficulty": "easy",
            "question": "physics easy question (10)",
            "answer": "2",
            "options": [
                "1",
                "2",
                "3",
                "4"
            ],
            "topic": "mechanics"
        },
        {
            "_id": "hard_11",
            "difficulty": "hard",
            "question": "physics hard question (11)",
            "answer": "3",
            "options": [
                "1",
                "2",
                "3",
                "4"
            ],
            "topic": "thermodynamics"
        },
        {
            "_id": "medium_12",
            "difficulty": "medium",
            "question": "physics medium question (12)",
            "answer": "4",
            "options": [
                "1",
                "2",
                "3",
                "4"
            ],
            "topic": "thermodynamics"
        },
        {
            "_id": "easy_13",
            "difficulty": "easy",
            "question": "physics easy question (13)",
            "answer": "1",
            "options": [
                "1",
                "2",
                "3",
                "4"
            ],
            "topic": "thermodynamics"
        },
        {
            "_id": "medium_14",
            "difficulty": "medium",
            "question": "physics medium question (14)",
            "answer": "2",
            "options": [
                "1",
                "2",
                "3",
                "4"
            ],
            "topic": "thermodynamics"
        },
        {
            "_id": "easy_15",
            "difficulty": "easy",
            "question": "physics easy question (15)",
            "answer": "3",
            "options": [
                "1",
                "2",
                "3",
                "4"
            ],
            "topic": "quantum mechanics"
        },
        {
            "_id": "easy_16",
            "difficulty": "easy",
            "question": "physics easy question (16)",
            "answer": "4",
            "options": [
                "1",
                "2",
                "3",
                "4"
            ],
            "topic": "quantum mechanics"
        },
        {
            "_id": "hard_17",
            "difficulty": "hard",
            "question": "physics hard question (17)",
            "answer": "1",
            "options": [
                "1",
                "2",
                "3",
                "4"
            ],
            "topic": "quantum mechanics"
        },
        {
            "_id": "medium_18",
            "difficulty": "medium",
            "question": "physics medium question (18)",
            "answer": "2",
            "options": [
                "1",
                "2",
                "3",
                "4"
            ],
            "topic": "quantum mechanics"
        },
        {
            "_id": "easy_19",
            "difficulty": "easy",
            "question": "physics easy question (19)",
            "answer": "3",
            "options": [
                "1",
                "2",
                "3",
                "4"
            ],
            "topic": "quantum mechanics"
        },
        {
            "_id": "easy_20",
            "difficulty": "easy",
            "question": "physics easy question (20)",
            "answer": "4",
            "options": [
                "1",
                "2",
                "3",
                "4"
            ],
            "topic": "quantum mechanics"
        }
    ]

}